picturedrocks/__init__.py
picturedrocks/_version.py
picturedrocks/performance.py
picturedrocks/plot.py
picturedrocks/preprocessing.py
picturedrocks/read.py
picturedrocks/markers/__init__.py
picturedrocks/markers/_iterative.py
picturedrocks/markers/interactive.py
picturedrocks/markers/mutualinformation/__init__.py
picturedrocks/markers/mutualinformation/infoset.py
picturedrocks/markers/mutualinformation/iterative.py
picturedrocks-1.0.2.dist-info/LICENSE
picturedrocks-1.0.2.dist-info/METADATA
picturedrocks-1.0.2.dist-info/WHEEL
picturedrocks-1.0.2.dist-info/top_level.txt
picturedrocks-1.0.2.dist-info/RECORD
