Metadata-Version: 2.1
Name: picturedrocks
Version: 1.0.2
Summary: Single Cell RNA Sequencing Marker Selection Package
Home-page: https://github.com/umangv/picturedrocks
Author: Umang Varma, Anna Gilbert
Author-email: uvarma@umich.edu
License: UNKNOWN
Platform: UNKNOWN
Classifier: Programming Language :: Python :: 3
Classifier: License :: OSI Approved :: GNU General Public License v3 (GPLv3)
Classifier: Operating System :: OS Independent
Requires-Python: ~=3.6
Requires-Dist: anndata
Requires-Dist: colorlover
Requires-Dist: h5py
Requires-Dist: numpy
Requires-Dist: pandas
Requires-Dist: plotly
Requires-Dist: scanpy
Requires-Dist: scipy
Requires-Dist: umap-learn
